{
    "tasks": [{
        "id": 1,
        "title": "test",
        "ownerId": 1,
        "comments": [{
            "id": 1,
            "value": "this is a comment",
            "author": {
                "id": 1,
                "name": "Tim"
            }
        }]
    }, {
        "id": 2,
        "title": "Task 2",
        "ownerId": 2,
        "comments": [{
            "id": 2,
            "value": "this is a comment",
            "author": {
                "id": 2,
                "name": "Cook"
            }
        }, {
            "id": 3,
            "value": "this is a comment",
            "author": {
                "id": 1,
                "name": "Tim"
            }
        }]
    }]
}